genai_apis/__init__.py
genai_apis/abstract.py
genai_apis/anthropic_api.py
genai_apis/factory.py
genai_apis/gemini_api.py
genai_apis/openai_api.py
genai_apis-0.0.10.dist-info/LICENSE
genai_apis-0.0.10.dist-info/METADATA
genai_apis-0.0.10.dist-info/WHEEL
genai_apis-0.0.10.dist-info/top_level.txt
genai_apis-0.0.10.dist-info/RECORD
